dafits/__init__.py
dafits/_version.py
dafits/io.py
dafits/version.pyi
dafits-2.0.0.dist-info/METADATA
dafits-2.0.0.dist-info/WHEEL
dafits-2.0.0.dist-info/licenses/LICENSE
dafits-2.0.0.dist-info/RECORD
