Metadata-Version: 2.4
Name: dafits
Version: 2.0.0
Summary: A package to produce produce FITS cubes.
Project-URL: Homepage, https://github.com/AlecThomson/da-fits
Project-URL: Bug Tracker, https://github.com/AlecThomson/da-fits/issues
Project-URL: Discussions, https://github.com/AlecThomson/da-fits/discussions
Project-URL: Changelog, https://github.com/AlecThomson/da-fits/releases
Author-email: Alec Thomson <alec.thomson@csiro.au>
License: MIT License
License-File: LICENSE
Classifier: Development Status :: 1 - Planning
Classifier: Intended Audience :: Developers
Classifier: Intended Audience :: Science/Research
Classifier: License :: OSI Approved :: BSD License
Classifier: Operating System :: OS Independent
Classifier: Programming Language :: Python
Classifier: Programming Language :: Python :: 3
Classifier: Programming Language :: Python :: 3 :: Only
Classifier: Programming Language :: Python :: 3.9
Classifier: Programming Language :: Python :: 3.10
Classifier: Programming Language :: Python :: 3.11
Classifier: Programming Language :: Python :: 3.12
Classifier: Topic :: Scientific/Engineering
Classifier: Typing :: Typed
Requires-Python: >=3.9
Requires-Dist: astropy>=6
Requires-Dist: dask
Requires-Dist: distributed
Provides-Extra: dev
Requires-Dist: pre-commit; extra == 'dev'
Requires-Dist: pytest-cov; extra == 'dev'
Requires-Dist: pytest-cov>=3; extra == 'dev'
Requires-Dist: pytest>=6; extra == 'dev'
Requires-Dist: ruff; extra == 'dev'
